PeaksValleys/PeaksValleys.py
PeaksValleys/__init__.py
PeaksValleys-1.2.2.dist-info/LICENSE
PeaksValleys-1.2.2.dist-info/METADATA
PeaksValleys-1.2.2.dist-info/WHEEL
PeaksValleys-1.2.2.dist-info/top_level.txt
PeaksValleys-1.2.2.dist-info/RECORD
