Metadata-Version: 2.1
Name: PeaksValleys
Version: 1.2.2
Summary: Detect peaks and valleys in a list of numbers
Home-page: https://github.com/PeaksValleys
Author: Ali Bahaari
Author-email: alibahaari1997@gmail.com
License: UNKNOWN
Project-URL: Bug Tracker, https://github.com/AliBahaari/PeaksValleys/issues
Platform: UNKNOWN
Classifier: Programming Language :: Python :: 3
Classifier: License :: OSI Approved :: MIT License
Classifier: Operating System :: OS Independent
Requires-Python: >=3.6
License-File: LICENSE
